is_even/__init__.py
is_even/__main__.py
isEvenAPI-3.0.dist-info/METADATA
isEvenAPI-3.0.dist-info/WHEEL
isEvenAPI-3.0.dist-info/entry_points.txt
isEvenAPI-3.0.dist-info/top_level.txt
isEvenAPI-3.0.dist-info/RECORD
