Metadata-Version: 2.1
Name: isEvenAPI
Version: 3.0
Summary: API Wrapper for the isEven API.
Home-page: https://github.com/UltiRequiem/isEvenAPI
Author: Eliaz Bobadilla
Author-email: eliaz.bobadilladev@gmail.com
License: MIT
Keywords: api,isEven,math,even,odd
Platform: UNKNOWN
Classifier: Operating System :: OS Independent
Requires-Dist: certifi (==2021.5.30)
Requires-Dist: coverage (==6.3.2)
Requires-Dist: chardet (==4.0.0)
Requires-Dist: decorator (==5.0.9)
Requires-Dist: idna (==2.10)
Requires-Dist: py (==1.10.0)
Requires-Dist: requests (==2.25.1)
Requires-Dist: retry (==0.9.2)
Requires-Dist: urllib3 (==1.26.5)
Requires-Dist: click (>=7.1.2)
Requires-Dist: typer (>=0.4.1)
